sloth_ci_ext_logs.py
sloth_ci_ext_logs-1.1.3.dist-info/LICENSE
sloth_ci_ext_logs-1.1.3.dist-info/WHEEL
sloth_ci_ext_logs-1.1.3.dist-info/METADATA
sloth_ci_ext_logs-1.1.3.dist-info/RECORD
